{
  "work_id": "더킹투하츠_05",
  "episode_no": 5,
  "scene_count": 56,
  "sequence_count": 8,
  "dramatic_question": "오보와 공개 고백이라는 혼돈 속에서 재하와 항아는 진심을 직면할 수 있을까?",
  "act_structure": [
    {
      "act": "설정",
      "seq_span": [
        1,
        2
      ],
      "beat": "WOC 해단 후 재하 귀환·왕실 재편과 함께 항아의 탈락 결정이 물밑에서 진행된다."
    },
    {
      "act": "전개",
      "seq_span": [
        3,
        5
      ],
      "beat": "탈락 통보 충격과 결혼 약속 오보가 겹치며 남북 왕실 모두 혼란에 빠지고, 재강의 해명 발표 강행으로 새로운 국면이 열린다."
    },
    {
      "act": "심화",
      "seq_span": [
        6,
        7
      ],
      "beat": "재하의 공개 고백이 여론을 뒤집고, 항아가 거부에서 자발적 수락으로 역전하며 두 사람의 진짜 대결이 예고된다."
    },
    {
      "act": "회말전환",
      "seq_span": [
        8,
        8
      ],
      "beat": "항아가 분계선을 넘어 제주도 왕실별장에 도착하고, 첫 대면의 긴장 속에서 재하의 화려한 이벤트가 펼쳐지며 로맨스 국면이 본격 시작된다."
    }
  ],
  "entry_state": "WOC 훈련이 막 종료되고 재하는 서울로 귀환하며 항아와의 이별 감정을 품고 있으나, 결혼 문제는 아직 물밑 단계다.",
  "exit_state": "항아가 남한에 입국해 제주도 별장에서 재하와 첫 상견례를 시작하고, 봉구가 한국행을 결심하면서 적대적 외부 위협이 본격화 된다.",
  "turning_point": {
    "seq_index": 6,
    "desc": "재하가 월드컵경기장에서 항아를 향한 공개 고백을 단행해 오보 위기를 로맨스 서사로 역전시키는 결정적 반전"
  },
  "central_conflict_axis": "재하의 충동적 진심 vs 항아의 자존심과 이념적 경계",
  "episode_function": "5회는 WOC 종료 직후 재하와 항아의 분리로 시작해, 결혼 약속 오보가 터지며 남북 왕실과 북한 조직 모두를 혼돈에 빠뜨리는 구조적 전환점이다. 재하의 공개 고백이라는 극적 반전으로 여론의 흐름을 로맨스로 전환시키고, 항아가 분노하면서도 끌려가는 감정의 균열을 보여준다. 제주도 상견례 착수로 두 주인공의 직접 대면이 시작되며, 봉구의 한국행 결심으로 적대적 외부세력이 본격 개입을 예고한다.",
  "core_dist": {
    "CONFLICT": 13,
    "REVERSAL": 10,
    "ROMANCE": 9,
    "ESTABLISH": 5,
    "PERIL": 5,
    "LOSS": 4,
    "REVELATION": 4,
    "DESIRE": 3,
    "ORACLE": 2,
    "BOND": 1
  },
  "by": "sonnet_reading"
}