{
  "work_id": "성균관스캔들_12",
  "episode_no": 12,
  "scene_count": 57,
  "sequence_count": 12,
  "dramatic_question": "선준은 자신이 느끼는 감정이 동방생에 대한 우정인지 사랑인지 끝까지 외면할 수 있는가, 그리고 재신의 공개적 구애는 윤희의 마음을 얻을 수 있는가?",
  "act_structure": [
    {
      "act": 1,
      "seq_span": [
        1,
        3
      ],
      "beat": "섬 고립 발단 — 배신감에서 시작된 우발적 고립이 두 사람을 극한 협력으로 밀어 넣고, 육지의 재신은 배편을 구하지 못하며 무력감 속에 마음을 들킨다."
    },
    {
      "act": 2,
      "seq_span": [
        4,
        8
      ],
      "beat": "감정 임계점 — 섬 밤의 로맨스가 키스 직전으로 치닫고 새벽 탈출과 효은 등장으로 상실이 확정된 뒤, 성균관 낮으로 무대가 전환되어 재신의 직구 고백과 선준의 자각이 교차하며 두 삼각관계가 동시에 끓어오른다."
    },
    {
      "act": 3,
      "seq_span": [
        9,
        11
      ],
      "beat": "정치·인간 복합 위기 — 가짜 홍벽서의 살생으로 정치 위기가 폭발하고, 입청재라는 공개 무대에서 모녀 재회·하인수 표적 지정·초선 거부가 겹치며 다층적 갈등이 동시에 임계점에 달한다."
    },
    {
      "act": 4,
      "seq_span": [
        12,
        12
      ],
      "beat": "피날레 훅 — 재신의 독서카드로 윤희의 시선이 바뀌고, 만찬에서 선준의 냉담함이 도화선이 되어 윤희의 반격과 초선의 충격적 키스가 터지며 다음 회를 향한 강력한 훅을 건다."
    }
  ],
  "entry_state": "선준과 윤희는 섬에 고립되어 감정적으로 위험한 상황에 처해 있으며, 재신은 윤희를 향한 마음을 억누르는 채 육지에서 배편을 구하지 못하고 있다.",
  "exit_state": "선준은 키스 직전 자신의 감정을 자각했으나 효은 앞에서 냉담하게 굴고 초선에게 충격적인 키스를 당하며 혼돈에 빠졌고, 재신의 독서카드를 발견한 윤희는 재신을 다른 눈으로 보기 시작했으며 하인수의 장치기 음모는 내일 발동 직전이다.",
  "turning_point": {
    "seq_index": 5,
    "desc": "선준이 잠든 윤희에게 키스 직전까지 다가갔다 스스로를 제지하는 새벽 장면(S20)에서 감정 자각이 확정되고, 이어 효은이 선준에게 달려가 안기는 것을 윤희가 목격하며(S23) 상실로 귀결되는 이중 반전이 회차 전체의 중추를 이룬다."
  },
  "central_conflict_axis": "이선준의 감정 자각(우정 vs 사랑)과 김윤희의 상실감, 그리고 문재신의 억누른 마음이 삼각으로 교차하는 감정 축 위에 하인수의 정치 음모와 홍벽서 위기가 외압으로 작동한다.",
  "episode_function": "12강은 섬 고립 밤을 통해 선준과 윤희의 감정이 임계점에 도달하는 전환 회차다. 선준이 키스 직전 스스로를 멈추며 감정을 자각하고, 재신도 윤희에 대한 마음을 용하에게 들키며 고백에 가까운 행동을 보인다. 후반부 입청재에서는 하인수의 장치기 음모, 가짜 홍벽서의 살생, 초선의 충격적인 키스로 다층적 긴장이 동시에 폭발하며 다음 회를 향한 강력한 훅을 건다.",
  "core_dist": {
    "CONFLICT": 7,
    "PERIL": 4,
    "REVERSAL": 4,
    "ROMANCE": 6,
    "REVELATION": 5,
    "BOND": 4,
    "RESCUE": 2,
    "DESIRE": 6,
    "RELIEF": 5,
    "HOOK": 2,
    "LOSS": 1,
    "ESTABLISH": 6,
    "ORACLE": 3,
    "PUNISH": 1,
    "REUNION": 1
  },
  "by": "sonnet_reading"
}